bedrock/__init__.py
bedrock/_demo.py
bedrock/consts.py
bedrock/context.py
bedrock/events.py
bedrock/exceptions.py
bedrock/ext/ui/__init__.py
bedrock/py.typed
bedrock/request.py
bedrock/response.py
bedrock/server.py
bedrock/utils.py
bedrockpy-1.0.1.dist-info/LICENSE
bedrockpy-1.0.1.dist-info/METADATA
bedrockpy-1.0.1.dist-info/WHEEL
bedrockpy-1.0.1.dist-info/RECORD
