Metadata-Version: 2.3
Name: bedrockpy
Version: 1.0.1
Summary: Minecraft: Bedrock Edition Websocket Server
License: MIT
Keywords: bedrock,minecraft,websocket
Author: Jonas da Silva
Maintainer: Bedrock WS
Maintainer-email: bedrock-ws@proton.me
Requires-Python: >=3.10,<4.0
Classifier: Intended Audience :: Education
Classifier: Intended Audience :: End Users/Desktop
Classifier: License :: OSI Approved :: MIT License
Classifier: Natural Language :: English
Classifier: Programming Language :: Python
Classifier: Programming Language :: Python :: 3
Classifier: Programming Language :: Python :: 3.10
Classifier: Programming Language :: Python :: 3.11
Classifier: Programming Language :: Python :: 3.12
Classifier: Programming Language :: Python :: 3.13
Classifier: Programming Language :: Python :: 3 :: Only
Classifier: Topic :: Education
Classifier: Topic :: Games/Entertainment
Classifier: Typing :: Typed
Provides-Extra: dev
Provides-Extra: docs
Provides-Extra: fast
Requires-Dist: attrs (>=23.2.0,<24.0.0)
Requires-Dist: convert-case (>=1.1.1,<2.0.0)
Requires-Dist: furo (>=2023.3.27,<2024.0.0) ; extra == "docs"
Requires-Dist: mypy (>=1.2.0,<2.0.0) ; extra == "dev"
Requires-Dist: myst-parser[linkify] (>=1.0.0,<2.0.0) ; extra == "docs"
Requires-Dist: sphinx (>=6.2.1,<7.0.0) ; extra == "docs"
Requires-Dist: sphinx-copybutton (>=0.5.2,<0.6.0) ; extra == "docs"
Requires-Dist: sphinx-design (>=0.4.1,<0.5.0) ; extra == "docs"
Requires-Dist: sphinx-notfound-page (>=0.8.3,<0.9.0) ; extra == "docs"
Requires-Dist: sphinxcontrib-mermaid (>=0.8.1,<0.9.0) ; extra == "docs"
Requires-Dist: sphinxcontrib-video (>=0.1.1,<0.2.0) ; extra == "docs"
Requires-Dist: tox (>=4.5.1,<5.0.0) ; extra == "dev"
Requires-Dist: uvloop (>=0.17.0,<0.18.0) ; extra == "fast"
Requires-Dist: websockets (>=11.0.2,<12.0.0)
Project-URL: Documentation, https://bedrockpy.readthedocs.io/
Project-URL: Repository, https://github.com/bedrock-ws/bedrockpy/
